sj.py
sj_test-1.3.dist-info/DESCRIPTION.rst
sj_test-1.3.dist-info/METADATA
sj_test-1.3.dist-info/RECORD
sj_test-1.3.dist-info/WHEEL
sj_test-1.3.dist-info/metadata.json
sj_test-1.3.dist-info/top_level.txt
