Metadata-Version: 2.0
Name: sj-test
Version: 1.3
Summary: SJ Python Source Code
Home-page: https://github.com/rampart81/pyquibase
Author: mokuzin21
Author-email: songew@gmail.com
License: UNKNOWN
Download-URL: https://githur.com/rampart81/pyquibase/archive/1.0.tar.gz
Keywords: smartlamp
Platform: UNKNOWN
Classifier: Programming Language :: Python :: 3
Classifier: Programming Language :: Python :: 3.2
Classifier: Programming Language :: Python :: 3.3
Classifier: Programming Language :: Python :: 3.4
Classifier: Programming Language :: Python :: 3.5
Classifier: Programming Language :: Python :: 3.6
Requires-Python: >=3
